binary_tree/__init__.py
binary_tree/frontend/build/asset-manifest.json
binary_tree/frontend/build/index.html
binary_tree/frontend/build/static/css/main.b99ffb9e.chunk.css
binary_tree/frontend/build/static/css/main.b99ffb9e.chunk.css.map
binary_tree/frontend/build/static/js/2.fc6b694a.chunk.js
binary_tree/frontend/build/static/js/2.fc6b694a.chunk.js.LICENSE.txt
binary_tree/frontend/build/static/js/2.fc6b694a.chunk.js.map
binary_tree/frontend/build/static/js/main.f8dcf137.chunk.js
binary_tree/frontend/build/static/js/main.f8dcf137.chunk.js.map
binary_tree/frontend/build/static/js/runtime-main.624f085e.js
binary_tree/frontend/build/static/js/runtime-main.624f085e.js.map
streamlit_binary_tree/__init__.py
streamlit_binary_tree/frontend/build/asset-manifest.json
streamlit_binary_tree/frontend/build/index.html
streamlit_binary_tree/frontend/build/static/css/main.216de144.chunk.css
streamlit_binary_tree/frontend/build/static/css/main.216de144.chunk.css.map
streamlit_binary_tree/frontend/build/static/css/main.3a4c9b92.chunk.css
streamlit_binary_tree/frontend/build/static/css/main.3a4c9b92.chunk.css.map
streamlit_binary_tree/frontend/build/static/css/main.9d901713.chunk.css
streamlit_binary_tree/frontend/build/static/css/main.9d901713.chunk.css.map
streamlit_binary_tree/frontend/build/static/css/main.b99ffb9e.chunk.css
streamlit_binary_tree/frontend/build/static/css/main.b99ffb9e.chunk.css.map
streamlit_binary_tree/frontend/build/static/js/2.41f15472.chunk.js
streamlit_binary_tree/frontend/build/static/js/2.41f15472.chunk.js.LICENSE.txt
streamlit_binary_tree/frontend/build/static/js/2.41f15472.chunk.js.map
streamlit_binary_tree/frontend/build/static/js/2.66fc388b.chunk.js
streamlit_binary_tree/frontend/build/static/js/2.66fc388b.chunk.js.LICENSE.txt
streamlit_binary_tree/frontend/build/static/js/2.66fc388b.chunk.js.map
streamlit_binary_tree/frontend/build/static/js/main.475c611d.chunk.js
streamlit_binary_tree/frontend/build/static/js/main.475c611d.chunk.js.map
streamlit_binary_tree-0.2.6.dist-info/LICENSE
streamlit_binary_tree-0.2.6.dist-info/METADATA
streamlit_binary_tree-0.2.6.dist-info/WHEEL
streamlit_binary_tree-0.2.6.dist-info/top_level.txt
streamlit_binary_tree-0.2.6.dist-info/RECORD
