Metadata-Version: 2.1
Name: streamlit-binary-tree
Version: 0.2.6
Summary: Interactive Binary Tree as a Streamlit component
Home-page: 
Author: Abhishek Sharma
Author-email: abhishek1995sharma@gmail.com
Requires-Python: >=3.6
License-File: LICENSE
Requires-Dist: streamlit (>=0.63)
Requires-Dist: scikit-learn
Requires-Dist: numpy
Requires-Dist: pandas
